pyfoam2sdf/__init__.py
pyfoam2sdf/pyfoam2sdf.py
pyfoam2sdf-1.1.dist-info/METADATA
pyfoam2sdf-1.1.dist-info/WHEEL
pyfoam2sdf-1.1.dist-info/top_level.txt
pyfoam2sdf-1.1.dist-info/RECORD
