Metadata-Version: 2.1
Name: pyfoam2sdf
Version: 1.1
Summary: A Python package for converting foamMesh data to Signed Distance Fields (SDF).
Home-page: https://github.com/srl-ethz/Foam-mesh-reading
Author: ZHANG Rushan
Author-email: rzhangbq@gmail.com
License: MIT
Classifier: Development Status :: 5 - Production/Stable
Classifier: Intended Audience :: Developers
Classifier: License :: OSI Approved :: MIT License
Classifier: Programming Language :: Python :: 3
Classifier: Programming Language :: Python :: 3.6
Classifier: Programming Language :: Python :: 3.7
Classifier: Programming Language :: Python :: 3.8
Classifier: Programming Language :: Python :: 3.9
Requires-Dist: numpy
